setup.cfg
setup.py
cliutils/__init__.py
cliutils/decorators.py
cliutils/persistence.py
cliutils/process.py
cliutils.egg-info/PKG-INFO
cliutils.egg-info/SOURCES.txt
cliutils.egg-info/dependency_links.txt
cliutils.egg-info/top_level.txt
cliutils.egg-info/zip-safe
cliutils/tests/test_decorators.py
cliutils/tests/test_persistence.py
cliutils/tests/test_process.py
docs/html/api-objects.txt
docs/html/class-tree.html
docs/html/cliutils-module.html
docs/html/cliutils-pysrc.html
docs/html/cliutils.decorators-module.html
docs/html/cliutils.decorators-pysrc.html
docs/html/cliutils.process-module.html
docs/html/cliutils.process-pysrc.html
docs/html/cliutils.process.AlreadyExecuted-class.html
docs/html/cliutils.process.InvalidCommand-class.html
docs/html/cliutils.process.Process-class.html
docs/html/cliutils.process._shell-class.html
docs/html/crarr.png
docs/html/epydoc.css
docs/html/epydoc.js
docs/html/frames.html
docs/html/help.html
docs/html/identifier-index.html
docs/html/index.html
docs/html/module-tree.html
docs/html/redirect.html
docs/html/toc-cliutils-module.html
docs/html/toc-cliutils.decorators-module.html
docs/html/toc-cliutils.process-module.html
docs/html/toc-everything.html
docs/html/toc.html
ez_setup/README.txt
ez_setup/__init__.py