Metadata-Version: 1.0
Name: cliutils
Version: 0.1.3
Summary: A collection of utilities easing the creation of command line scripts
Home-page: http://code.google.com/p/cliutils
Author: Ian McCracken
Author-email: ian.mccracken@gmail.com
License: MIT License
Platform: UNKNOWN
Classifier: Intended Audience :: Developers
Classifier: Intended Audience :: System Administrators
Classifier: License :: OSI Approved :: MIT License
Classifier: Programming Language :: Python
Classifier: Topic :: Software Development :: Libraries :: Python Modules
